hexrec/__init__.py
hexrec/__main__.py
hexrec/base.py
hexrec/cli.py
hexrec/hexdump.py
hexrec/utils.py
hexrec/xxd.py
hexrec/formats/__init__.py
hexrec/formats/asciihex.py
hexrec/formats/avr.py
hexrec/formats/ihex.py
hexrec/formats/mos.py
hexrec/formats/raw.py
hexrec/formats/sqtp.py
hexrec/formats/srec.py
hexrec/formats/titxt.py
hexrec/formats/xtek.py
hexrec-0.5.1.dist-info/licenses/AUTHORS.rst
hexrec-0.5.1.dist-info/licenses/LICENSE
hexrec-0.5.1.dist-info/METADATA
hexrec-0.5.1.dist-info/WHEEL
hexrec-0.5.1.dist-info/entry_points.txt
hexrec-0.5.1.dist-info/top_level.txt
hexrec-0.5.1.dist-info/RECORD
