Metadata-Version: 2.4
Name: hexrec
Version: 0.5.1
Summary: Library to handle hexadecimal record files
Author-email: Andrea Zoppi <texzk@email.it>
License-Expression: BSD-2-Clause
Project-URL: documentation, https://hexrec.readthedocs.io/en/latest/
Project-URL: source, https://github.com/TexZK/hexrec/
Project-URL: tracker, https://github.com/TexZK/hexrec/issues/
Classifier: Development Status :: 4 - Beta
Classifier: Intended Audience :: Developers
Classifier: Operating System :: OS Independent
Classifier: Programming Language :: Python
Classifier: Programming Language :: Python :: 3
Classifier: Programming Language :: Python :: 3 :: Only
Classifier: Programming Language :: Python :: 3.9
Classifier: Programming Language :: Python :: 3.10
Classifier: Programming Language :: Python :: 3.11
Classifier: Programming Language :: Python :: 3.12
Classifier: Programming Language :: Python :: 3.13
Classifier: Programming Language :: Python :: 3.14
Classifier: Programming Language :: Python :: Implementation :: CPython
Classifier: Programming Language :: Python :: Implementation :: PyPy
Classifier: Topic :: Scientific/Engineering :: Interface Engine/Protocol Translator
Classifier: Topic :: Software Development
Classifier: Topic :: Software Development :: Embedded Systems
Classifier: Topic :: Utilities
Requires-Python: >=3.9
License-File: LICENSE
License-File: AUTHORS.rst
Requires-Dist: bytesparse>=1.0.0
Requires-Dist: click
Requires-Dist: colorama
Provides-Extra: testing
Requires-Dist: coverage; extra == "testing"
Requires-Dist: pyelftools; extra == "testing"
Requires-Dist: pytest; extra == "testing"
Dynamic: license-file
